collibra_protect/__init__.py
collibra_protect/api_client.py
collibra_protect/configuration.py
collibra_protect/rest.py
collibra_protect/api/__init__.py
collibra_protect/api/custom_maskings_api.py
collibra_protect/api/data_sources_api.py
collibra_protect/api/groups_api.py
collibra_protect/api/prescriptive_paths_api.py
collibra_protect/models/__init__.py
collibra_protect/models/add_custom_masking_request.py
collibra_protect/models/add_data_source_request.py
collibra_protect/models/add_group_request.py
collibra_protect/models/add_prescriptive_path_request.py
collibra_protect/models/asset_type_ids.py
collibra_protect/models/change_custom_masking_request.py
collibra_protect/models/change_data_source_request.py
collibra_protect/models/change_group_request.py
collibra_protect/models/change_prescriptive_path_request.py
collibra_protect/models/cursors.py
collibra_protect/models/custom_masking.py
collibra_protect/models/data_source.py
collibra_protect/models/data_source_alias.py
collibra_protect/models/editable_custom_masking.py
collibra_protect/models/editable_data_source.py
collibra_protect/models/editable_group.py
collibra_protect/models/editable_prescriptive_path.py
collibra_protect/models/group.py
collibra_protect/models/group_mapping.py
collibra_protect/models/masking_mapping.py
collibra_protect/models/paged_custom_maskings.py
collibra_protect/models/paged_data_sources.py
collibra_protect/models/paged_groups.py
collibra_protect/models/prescriptive_path.py
collibra_protect/models/prescriptive_path_asset_type.py
collibra_protect/models/prescriptive_path_relation.py
collibra_protect/models/prescriptive_paths.py
collibra_protect/models/provider.py
collibra_protect/models/provider_masking_mappings.py
collibra_protect/models/relation_type_direction.py
collibra_protect/models/standard_error_response.py
test/__init__.py
test/test_add_custom_masking_request.py
test/test_add_data_source_request.py
test/test_add_group_request.py
test/test_add_prescriptive_path_request.py
collibra_protect_100-1.0.0.dist-info/METADATA
collibra_protect_100-1.0.0.dist-info/WHEEL
collibra_protect_100-1.0.0.dist-info/top_level.txt
collibra_protect_100-1.0.0.dist-info/RECORD
